{
  "date": "2025-12-31",
  "model": "Variant B",
  "min_edge": 0.1,
  "kelly_fraction": 0.25,
  "bankroll": 10000.0,
  "num_picks": 15,
  "total_bet_size": 12910,
  "avg_edge": 0.29179015223482213,
  "max_edge": 0.4901852968377841,
  "picks": [
    {
      "date": "2025-12-31",
      "home_team": "Old Dominion Monarchs",
      "away_team": "Appalachian St Mountaineers",
      "side": "away",
      "odds": 118,
      "model_prob": 0.9489008931680594,
      "implied_prob": 0.45871559633027525,
      "edge": 0.4901852968377841,
      "kelly_full": 0.4154112685065968,
      "kelly_applied": 0.1,
      "bet_size_dollars": 1000,
      "market": "away_ml"
    },
    {
      "date": "2025-12-31",
      "home_team": "Navy Midshipmen",
      "away_team": "Boston Univ. Terriers",
      "side": "away",
      "odds": 210,
      "model_prob": 0.7561784375579715,
      "implied_prob": 0.3225806451612903,
      "edge": 0.4335977923966812,
      "kelly_full": 0.20647513923651487,
      "kelly_applied": 0.051618784809128716,
      "bet_size_dollars": 516,
      "market": "away_ml"
    },
    {
      "date": "2025-12-31",
      "home_team": "North Carolina A&T Aggies",
      "away_team": "Northeastern",
      "side": "away",
      "odds": -168,
      "model_prob": 0.9817002423169434,
      "implied_prob": 0.6268656716417911,
      "edge": 0.35483457067515234,
      "kelly_full": 0.5961220787342558,
      "kelly_applied": 0.1,
      "bet_size_dollars": 1000,
      "market": "away_ml"
    },
    {
      "date": "2025-12-31",
      "home_team": "East Texas A&M Lions",
      "away_team": "Lamar",
      "side": "away",
      "odds": -176,
      "model_prob": 0.9753448617407963,
      "implied_prob": 0.6376811594202898,
      "edge": 0.33766370232050646,
      "kelly_full": 0.5942881160840912,
      "kelly_applied": 0.1,
      "bet_size_dollars": 1000,
      "market": "away_ml"
    },
    {
      "date": "2025-12-31",
      "home_team": "South Carolina Upstate",
      "away_team": "Radford Highlanders",
      "side": "away",
      "odds": -110,
      "model_prob": 0.8557107920208769,
      "implied_prob": 0.5238095238095238,
      "edge": 0.331901268211353,
      "kelly_full": 0.3650913950324883,
      "kelly_applied": 0.09127284875812207,
      "bet_size_dollars": 913,
      "market": "away_ml"
    },
    {
      "date": "2025-12-31",
      "home_team": "Monmouth Hawks",
      "away_team": "Campbell Fighting Camels",
      "side": "away",
      "odds": -105,
      "model_prob": 0.8220467145432997,
      "implied_prob": 0.5121951219512195,
      "edge": 0.30985159259208017,
      "kelly_full": 0.3253441722216842,
      "kelly_applied": 0.08133604305542105,
      "bet_size_dollars": 813,
      "market": "away_ml"
    },
    {
      "date": "2025-12-31",
      "home_team": "East Carolina Pirates",
      "away_team": "Tulane Green Wave",
      "side": "away",
      "odds": -126,
      "model_prob": 0.8527966806915256,
      "implied_prob": 0.5575221238938053,
      "edge": 0.2952745567977203,
      "kelly_full": 0.37204594156512766,
      "kelly_applied": 0.09301148539128191,
      "bet_size_dollars": 930,
      "market": "away_ml"
    },
    {
      "date": "2025-12-31",
      "home_team": "Hampton Pirates",
      "away_team": "Towson",
      "side": "away",
      "odds": -250,
      "model_prob": 0.994464486497178,
      "implied_prob": 0.7142857142857143,
      "edge": 0.2801787722114637,
      "kelly_full": 0.7004469305286594,
      "kelly_applied": 0.1,
      "bet_size_dollars": 1000,
      "market": "away_ml"
    },
    {
      "date": "2025-12-31",
      "home_team": "Holy Cross Crusaders",
      "away_team": "Bucknell Bison",
      "side": "home",
      "odds": -118,
      "model_prob": 0.808718612422534,
      "implied_prob": 0.5412844036697247,
      "edge": 0.2674342087528092,
      "kelly_full": 0.31557236632831487,
      "kelly_applied": 0.07889309158207872,
      "bet_size_dollars": 789,
      "market": "home_ml"
    },
    {
      "date": "2025-12-31",
      "home_team": "Western Carolina Catamounts",
      "away_team": "Wofford Terriers",
      "side": "home",
      "odds": 102,
      "model_prob": 0.7443452149286023,
      "implied_prob": 0.49504950495049505,
      "edge": 0.24929570997810724,
      "kelly_full": 0.2444075588020659,
      "kelly_applied": 0.06110188970051648,
      "bet_size_dollars": 611,
      "market": "home_ml"
    },
    {
      "date": "2025-12-31",
      "home_team": "Northern Illinois",
      "away_team": "Buffalo Bulls",
      "side": "away",
      "odds": -290,
      "model_prob": 0.9905090217584223,
      "implied_prob": 0.7435897435897436,
      "edge": 0.24691927816867865,
      "kelly_full": 0.716065906689168,
      "kelly_applied": 0.1,
      "bet_size_dollars": 1000,
      "market": "away_ml"
    },
    {
      "date": "2025-12-31",
      "home_team": "Virginia Tech Hokies",
      "away_team": "Virginia Cavaliers",
      "side": "away",
      "odds": -235,
      "model_prob": 0.9317760117316687,
      "implied_prob": 0.7014925373134329,
      "edge": 0.23028347441823582,
      "kelly_full": 0.5411661648828543,
      "kelly_applied": 0.1,
      "bet_size_dollars": 1000,
      "market": "away_ml"
    },
    {
      "date": "2025-12-31",
      "home_team": "Texas A&M-CC Islanders",
      "away_team": "New Orleans Privateers",
      "side": "away",
      "odds": 164,
      "model_prob": 0.6002962471021394,
      "implied_prob": 0.3787878787878788,
      "edge": 0.22150836831426057,
      "kelly_full": 0.13506607824040281,
      "kelly_applied": 0.033766519560100704,
      "bet_size_dollars": 338,
      "market": "away_ml"
    },
    {
      "date": "2025-12-31",
      "home_team": "Northwestern St Demons",
      "away_team": "Stephen F. Austin Lumberjacks",
      "side": "away",
      "odds": -385,
      "model_prob": 0.9713843797565361,
      "implied_prob": 0.7938144329896907,
      "edge": 0.17756994676684545,
      "kelly_full": 0.6836442950523548,
      "kelly_applied": 0.1,
      "bet_size_dollars": 1000,
      "market": "away_ml"
    },
    {
      "date": "2025-12-31",
      "home_team": "Troy Trojans",
      "away_team": "Texas State Bobcats",
      "side": "home",
      "odds": -480,
      "model_prob": 0.9779399519772055,
      "implied_prob": 0.8275862068965517,
      "edge": 0.1503537450806538,
      "kelly_full": 0.7216979763871385,
      "kelly_applied": 0.1,
      "bet_size_dollars": 1000,
      "market": "home_ml"
    }
  ]
}