{
  "date": "2025-12-13",
  "model": "Variant B",
  "min_edge": 0.1,
  "kelly_fraction": 0.25,
  "bankroll": 10000.0,
  "num_picks": 26,
  "total_bet_size": 23917,
  "avg_edge": 0.3221248960430461,
  "max_edge": 0.5517720724811144,
  "picks": [
    {
      "date": "2025-12-13",
      "home_team": "Denver Pioneers",
      "away_team": "CSU Fullerton Titans",
      "side": "away",
      "odds": 176,
      "model_prob": 0.9140909130608246,
      "implied_prob": 0.36231884057971014,
      "edge": 0.5517720724811144,
      "kelly_full": 0.3135068593642696,
      "kelly_applied": 0.0783767148410674,
      "bet_size_dollars": 784,
      "market": "away_ml"
    },
    {
      "date": "2025-12-13",
      "home_team": "Dartmouth Big Green",
      "away_team": "Boston Univ. Terriers",
      "side": "away",
      "odds": 130,
      "model_prob": 0.9524665691044197,
      "implied_prob": 0.43478260869565216,
      "edge": 0.5176839604087675,
      "kelly_full": 0.3982184310836674,
      "kelly_applied": 0.09955460777091685,
      "bet_size_dollars": 996,
      "market": "away_ml"
    },
    {
      "date": "2025-12-13",
      "home_team": "LIU Sharks",
      "away_team": "La Salle Explorers",
      "side": "away",
      "odds": 126,
      "model_prob": 0.9575587313924476,
      "implied_prob": 0.4424778761061947,
      "edge": 0.5150808552862529,
      "kelly_full": 0.4087943295922643,
      "kelly_applied": 0.1,
      "bet_size_dollars": 1000,
      "market": "away_ml"
    },
    {
      "date": "2025-12-13",
      "home_team": "Houston Christian",
      "away_team": "SE Louisiana Lions",
      "side": "away",
      "odds": 122,
      "model_prob": 0.9479657012508856,
      "implied_prob": 0.45045045045045046,
      "edge": 0.4975152508004352,
      "kelly_full": 0.40779938590199616,
      "kelly_applied": 0.1,
      "bet_size_dollars": 1000,
      "market": "away_ml"
    },
    {
      "date": "2025-12-14",
      "home_team": "CSU Bakersfield Roadrunners",
      "away_team": "Pepperdine Waves",
      "side": "away",
      "odds": 120,
      "model_prob": 0.9513157770897589,
      "implied_prob": 0.45454545454545453,
      "edge": 0.49677032254430437,
      "kelly_full": 0.41397526878692026,
      "kelly_applied": 0.1,
      "bet_size_dollars": 1000,
      "market": "away_ml"
    },
    {
      "date": "2025-12-13",
      "home_team": "Morgan St",
      "away_team": "Niagara Purple Eagles",
      "side": "away",
      "odds": 104,
      "model_prob": 0.9684956483331584,
      "implied_prob": 0.49019607843137253,
      "edge": 0.47829956990178585,
      "kelly_full": 0.459903432597871,
      "kelly_applied": 0.1,
      "bet_size_dollars": 1000,
      "market": "away_ml"
    },
    {
      "date": "2025-12-13",
      "home_team": "Wichita St Shockers",
      "away_team": "DePaul Blue Demons",
      "side": "away",
      "odds": 220,
      "model_prob": 0.7077580610616465,
      "implied_prob": 0.3125,
      "edge": 0.3952580610616465,
      "kelly_full": 0.17966275502802112,
      "kelly_applied": 0.04491568875700528,
      "bet_size_dollars": 449,
      "market": "away_ml"
    },
    {
      "date": "2025-12-13",
      "home_team": "Loyola (MD) Greyhounds",
      "away_team": "Mt. St. Mary's Mountaineers",
      "side": "away",
      "odds": -118,
      "model_prob": 0.9089691269114771,
      "implied_prob": 0.5412844036697247,
      "edge": 0.3676847232417524,
      "kelly_full": 0.43386797342526784,
      "kelly_applied": 0.1,
      "bet_size_dollars": 1000,
      "market": "away_ml"
    },
    {
      "date": "2025-12-13",
      "home_team": "Rice Owls",
      "away_team": "Arkansas St Red Wolves",
      "side": "away",
      "odds": -158,
      "model_prob": 0.9762153906211356,
      "implied_prob": 0.6124031007751938,
      "edge": 0.3638122898459418,
      "kelly_full": 0.5748234179565881,
      "kelly_applied": 0.1,
      "bet_size_dollars": 1000,
      "market": "away_ml"
    },
    {
      "date": "2025-12-13",
      "home_team": "UNC Asheville",
      "away_team": "St. Thomas (MN) Tommies",
      "side": "away",
      "odds": -162,
      "model_prob": 0.9752013400941665,
      "implied_prob": 0.6183206106870229,
      "edge": 0.35688072940714355,
      "kelly_full": 0.5781467816395724,
      "kelly_applied": 0.1,
      "bet_size_dollars": 1000,
      "market": "away_ml"
    },
    {
      "date": "2025-12-13",
      "home_team": "Georgia St Panthers",
      "away_team": "Jacksonville St Gamecocks",
      "side": "away",
      "odds": -215,
      "model_prob": 0.98956547906903,
      "implied_prob": 0.6825396825396826,
      "edge": 0.30702579652934747,
      "kelly_full": 0.6601054625380971,
      "kelly_applied": 0.1,
      "bet_size_dollars": 1000,
      "market": "away_ml"
    },
    {
      "date": "2025-12-13",
      "home_team": "Howard Bison",
      "away_team": "Hampton Pirates",
      "side": "away",
      "odds": -184,
      "model_prob": 0.9519530804637458,
      "implied_prob": 0.647887323943662,
      "edge": 0.30406575652008383,
      "kelly_full": 0.5594809919969542,
      "kelly_applied": 0.1,
      "bet_size_dollars": 1000,
      "market": "away_ml"
    },
    {
      "date": "2025-12-13",
      "home_team": "Bryant",
      "away_team": "Marist Red Foxes",
      "side": "away",
      "odds": -205,
      "model_prob": 0.9753448617407963,
      "implied_prob": 0.6721311475409836,
      "edge": 0.3032137141998127,
      "kelly_full": 0.621588114109616,
      "kelly_applied": 0.1,
      "bet_size_dollars": 1000,
      "market": "away_ml"
    },
    {
      "date": "2025-12-13",
      "home_team": "Richmond Spiders",
      "away_team": "Southern Illinois Salukis",
      "side": "home",
      "odds": -210,
      "model_prob": 0.9757630220457268,
      "implied_prob": 0.6774193548387096,
      "edge": 0.2983436672070172,
      "kelly_full": 0.626521701134736,
      "kelly_applied": 0.1,
      "bet_size_dollars": 1000,
      "market": "home_ml"
    },
    {
      "date": "2025-12-13",
      "home_team": "Bellarmine Knights",
      "away_team": "Northern Kentucky Norse",
      "side": "away",
      "odds": -215,
      "model_prob": 0.9622516868272084,
      "implied_prob": 0.6825396825396826,
      "edge": 0.27971200428752585,
      "kelly_full": 0.6013808092181807,
      "kelly_applied": 0.1,
      "bet_size_dollars": 1000,
      "market": "away_ml"
    },
    {
      "date": "2025-12-13",
      "home_team": "Valparaiso Beacons",
      "away_team": "UNC Wilmington Seahawks",
      "side": "away",
      "odds": -250,
      "model_prob": 0.9887443325157774,
      "implied_prob": 0.7142857142857143,
      "edge": 0.2744586182300631,
      "kelly_full": 0.686146545575158,
      "kelly_applied": 0.1,
      "bet_size_dollars": 1000,
      "market": "away_ml"
    },
    {
      "date": "2025-12-14",
      "home_team": "UC San Diego Tritons",
      "away_team": "Tulane Green Wave",
      "side": "home",
      "odds": -245,
      "model_prob": 0.98031311488104,
      "implied_prob": 0.7101449275362319,
      "edge": 0.2701681873448081,
      "kelly_full": 0.6619120589947798,
      "kelly_applied": 0.1,
      "bet_size_dollars": 1000,
      "market": "home_ml"
    },
    {
      "date": "2025-12-13",
      "home_team": "Eastern Kentucky Colonels",
      "away_team": "Miami (OH) RedHawks",
      "side": "away",
      "odds": -280,
      "model_prob": 0.990954897664164,
      "implied_prob": 0.7368421052631579,
      "edge": 0.25411279240100615,
      "kelly_full": 0.7115158187228171,
      "kelly_applied": 0.1,
      "bet_size_dollars": 1000,
      "market": "away_ml"
    },
    {
      "date": "2025-12-13",
      "home_team": "Tulsa Golden Hurricane",
      "away_team": "New Mexico St Aggies",
      "side": "away",
      "odds": 215,
      "model_prob": 0.5651215682609463,
      "implied_prob": 0.31746031746031744,
      "edge": 0.24766125080062884,
      "kelly_full": 0.11519127944215296,
      "kelly_applied": 0.02879781986053824,
      "bet_size_dollars": 288,
      "market": "away_ml"
    },
    {
      "date": "2025-12-14",
      "home_team": "West Georgia Wolves",
      "away_team": "Georgia Southern Eagles",
      "side": "away",
      "odds": -220,
      "model_prob": 0.9080974491836048,
      "implied_prob": 0.6875,
      "edge": 0.2205974491836048,
      "kelly_full": 0.4853143882039305,
      "kelly_applied": 0.1,
      "bet_size_dollars": 1000,
      "market": "away_ml"
    },
    {
      "date": "2025-12-14",
      "home_team": "Ohio State Buckeyes",
      "away_team": "West Virginia Mountaineers",
      "side": "home",
      "odds": -205,
      "model_prob": 0.8795951035762931,
      "implied_prob": 0.6721311475409836,
      "edge": 0.20746395603530954,
      "kelly_full": 0.42530110987238456,
      "kelly_applied": 0.1,
      "bet_size_dollars": 1000,
      "market": "home_ml"
    },
    {
      "date": "2025-12-13",
      "home_team": "Oklahoma Sooners",
      "away_team": "Oklahoma St Cowboys",
      "side": "away",
      "odds": 112,
      "model_prob": 0.650693698381124,
      "implied_prob": 0.4716981132075472,
      "edge": 0.17899558517357683,
      "kelly_full": 0.15981748676212215,
      "kelly_applied": 0.03995437169053054,
      "bet_size_dollars": 400,
      "market": "away_ml"
    },
    {
      "date": "2025-12-13",
      "home_team": "Northern Iowa Panthers",
      "away_team": "Oakland Golden Grizzlies",
      "side": "home",
      "odds": -430,
      "model_prob": 0.9886358492636907,
      "implied_prob": 0.8113207547169812,
      "edge": 0.17731509454670957,
      "kelly_full": 0.7624549065508512,
      "kelly_applied": 0.1,
      "bet_size_dollars": 1000,
      "market": "home_ml"
    },
    {
      "date": "2025-12-13",
      "home_team": "Binghamton Bearcats",
      "away_team": "Central Connecticut St",
      "side": "away",
      "odds": -385,
      "model_prob": 0.9664893076617462,
      "implied_prob": 0.7938144329896907,
      "edge": 0.17267487467205556,
      "kelly_full": 0.6647982674874137,
      "kelly_applied": 0.1,
      "bet_size_dollars": 1000,
      "market": "away_ml"
    },
    {
      "date": "2025-12-14",
      "home_team": "Nevada Wolf Pack",
      "away_team": "Duquesne Dukes",
      "side": "home",
      "odds": -375,
      "model_prob": 0.9604304219446081,
      "implied_prob": 0.7894736842105263,
      "edge": 0.17095673773408182,
      "kelly_full": 0.641087766502807,
      "kelly_applied": 0.1,
      "bet_size_dollars": 1000,
      "market": "home_ml"
    },
    {
      "date": "2025-12-13",
      "home_team": "Fordham Rams",
      "away_team": "Manhattan Jaspers",
      "side": "home",
      "odds": -450,
      "model_prob": 0.9859057954562401,
      "implied_prob": 0.8181818181818182,
      "edge": 0.1677239772744219,
      "kelly_full": 0.7547578977348982,
      "kelly_applied": 0.1,
      "bet_size_dollars": 1000,
      "market": "home_ml"
    }
  ]
}